src/cli/__init__.py
src/cli/api.py
src/cli/bucket.py
src/cli/commons.py
src/cli/exceptions.py
src/cli/main.py
src/cli/user.py
adacord_cli-0.1.1.dist-info/entry_points.txt
adacord_cli-0.1.1.dist-info/WHEEL
adacord_cli-0.1.1.dist-info/METADATA
adacord_cli-0.1.1.dist-info/RECORD
