Metadata-Version: 2.1
Name: adacord-cli
Version: 0.1.1
Summary: Adacord CLI
Author: Christian Barra
Author-email: me@christianbarra.com
Requires-Python: >=3.8,<4.0
Classifier: Programming Language :: Python :: 3
Classifier: Programming Language :: Python :: 3.10
Classifier: Programming Language :: Python :: 3.8
Classifier: Programming Language :: Python :: 3.9
Requires-Dist: requests (>=2.26.0,<3.0.0)
Requires-Dist: tabulate (>=0.8.9,<0.9.0)
Requires-Dist: typer[all] (>=0.3.2,<0.4.0)
